cirkit/__init__.py
cirkit/pipeline.py
cirkit/backend/__init__.py
cirkit/backend/base.py
cirkit/backend/compiler.py
cirkit/backend/registry.py
cirkit/backend/torch/__init__.py
cirkit/backend/torch/circuits.py
cirkit/backend/torch/compiler.py
cirkit/backend/torch/initializers.py
cirkit/backend/torch/queries.py
cirkit/backend/torch/semiring.py
cirkit/backend/torch/utils.py
cirkit/backend/torch/graph/__init__.py
cirkit/backend/torch/graph/folding.py
cirkit/backend/torch/graph/modules.py
cirkit/backend/torch/graph/optimize.py
cirkit/backend/torch/layers/__init__.py
cirkit/backend/torch/layers/base.py
cirkit/backend/torch/layers/inner.py
cirkit/backend/torch/layers/input.py
cirkit/backend/torch/layers/optimized.py
cirkit/backend/torch/optimization/__init__.py
cirkit/backend/torch/optimization/layers.py
cirkit/backend/torch/optimization/parameters.py
cirkit/backend/torch/optimization/registry.py
cirkit/backend/torch/parameters/__init__.py
cirkit/backend/torch/parameters/nodes.py
cirkit/backend/torch/parameters/optimized.py
cirkit/backend/torch/parameters/parameter.py
cirkit/backend/torch/parameters/pic.py
cirkit/backend/torch/rules/__init__.py
cirkit/backend/torch/rules/initializers.py
cirkit/backend/torch/rules/layers.py
cirkit/backend/torch/rules/parameters.py
cirkit/symbolic/__init__.py
cirkit/symbolic/circuit.py
cirkit/symbolic/dtypes.py
cirkit/symbolic/functional.py
cirkit/symbolic/initializers.py
cirkit/symbolic/io.py
cirkit/symbolic/layers.py
cirkit/symbolic/operators.py
cirkit/symbolic/parameters.py
cirkit/symbolic/registry.py
cirkit/templates/__init__.py
cirkit/templates/data_modalities.py
cirkit/templates/pgms.py
cirkit/templates/tensor_factorizations.py
cirkit/templates/utils.py
cirkit/templates/logic/__init__.py
cirkit/templates/logic/graph.py
cirkit/templates/logic/sdd.py
cirkit/templates/logic/utils.py
cirkit/templates/region_graph/__init__.py
cirkit/templates/region_graph/graph.py
cirkit/templates/region_graph/algorithms/__init__.py
libcirkit-0.2.0.dist-info/LICENSE
libcirkit-0.2.0.dist-info/METADATA
libcirkit-0.2.0.dist-info/WHEEL
libcirkit-0.2.0.dist-info/top_level.txt
libcirkit-0.2.0.dist-info/RECORD
